Metadata-Version: 1.0
Name: myfirstdlr
Version: 0.0.11
Summary: testing...
Home-page: https://google.com
Author: whoami
Author-email: wai@yy.com
License: UNKNOWN
Platform: UNKNOWN
